api5paisa/__init__.py
api5paisa/api5paisa.py
api5paisa-0.0.9.dist-info/LICENSE
api5paisa-0.0.9.dist-info/METADATA
api5paisa-0.0.9.dist-info/WHEEL
api5paisa-0.0.9.dist-info/top_level.txt
api5paisa-0.0.9.dist-info/RECORD
