Metadata-Version: 2.1
Name: api5paisa
Version: 0.0.9
Summary: Unoffical Browser Based Python API of 5paisa
Home-page: https://github.com/aeron7/api5paisa
Author: Aeron7
Author-email: hello@aeron7.com
License: UNKNOWN
Keywords: 5paisa,5paisa api,python,sdk,trading,stock markets
Platform: UNKNOWN
Classifier: Intended Audience :: Developers
Classifier: Natural Language :: English
Classifier: Operating System :: OS Independent
Classifier: Programming Language :: Python
Classifier: Programming Language :: Python :: 3
Classifier: Programming Language :: Python :: Implementation :: PyPy
Classifier: Topic :: Software Development :: Libraries :: Python Modules
Requires-Dist: requests
Requires-Dist: pandas
